IbmDeveloperworksQuanbuJiaochengEr/README.md
IbmDeveloperworksQuanbuJiaochengEr/__init__.py
IbmDeveloperworksQuanbuJiaochengEr/__main__.py
IbmDeveloperworksQuanbuJiaochengEr/file.epub
IbmDeveloperworksQuanbuJiaochengEr/index.html
IbmDeveloperworksQuanbuJiaochengEr/css/__init__.py
IbmDeveloperworksQuanbuJiaochengEr/css/annotations.css
IbmDeveloperworksQuanbuJiaochengEr/css/main.css
IbmDeveloperworksQuanbuJiaochengEr/css/normalize.css
IbmDeveloperworksQuanbuJiaochengEr/css/popup.css
IbmDeveloperworksQuanbuJiaochengEr/font/__init__.py
IbmDeveloperworksQuanbuJiaochengEr/font/fontello.eot
IbmDeveloperworksQuanbuJiaochengEr/font/fontello.svg
IbmDeveloperworksQuanbuJiaochengEr/font/fontello.ttf
IbmDeveloperworksQuanbuJiaochengEr/font/fontello.woff
IbmDeveloperworksQuanbuJiaochengEr/img/__init__.py
IbmDeveloperworksQuanbuJiaochengEr/img/annotator-glyph-sprite.png
IbmDeveloperworksQuanbuJiaochengEr/img/annotator-icon-sprite.png
IbmDeveloperworksQuanbuJiaochengEr/img/apple-touch-icon.png
IbmDeveloperworksQuanbuJiaochengEr/img/cancelfullscreen.png
IbmDeveloperworksQuanbuJiaochengEr/img/close.png
IbmDeveloperworksQuanbuJiaochengEr/img/fullscreen.png
IbmDeveloperworksQuanbuJiaochengEr/img/loader.gif
IbmDeveloperworksQuanbuJiaochengEr/img/menu-icon.png
IbmDeveloperworksQuanbuJiaochengEr/img/save.png
IbmDeveloperworksQuanbuJiaochengEr/img/saved.png
IbmDeveloperworksQuanbuJiaochengEr/img/settings-s.png
IbmDeveloperworksQuanbuJiaochengEr/img/settings.png
IbmDeveloperworksQuanbuJiaochengEr/img/star.png
IbmDeveloperworksQuanbuJiaochengEr/js/__init__.py
IbmDeveloperworksQuanbuJiaochengEr/js/epub.js
IbmDeveloperworksQuanbuJiaochengEr/js/epub.min.js
IbmDeveloperworksQuanbuJiaochengEr/js/epub.min.map
IbmDeveloperworksQuanbuJiaochengEr/js/hooks.min.js
IbmDeveloperworksQuanbuJiaochengEr/js/hooks.min.map
IbmDeveloperworksQuanbuJiaochengEr/js/reader.js
IbmDeveloperworksQuanbuJiaochengEr/js/reader.js.map
IbmDeveloperworksQuanbuJiaochengEr/js/reader.min.js
ibm_developerworks_quanbu_jiaocheng_er-2024.3.6.0.dist-info/METADATA
ibm_developerworks_quanbu_jiaocheng_er-2024.3.6.0.dist-info/WHEEL
ibm_developerworks_quanbu_jiaocheng_er-2024.3.6.0.dist-info/entry_points.txt
ibm_developerworks_quanbu_jiaocheng_er-2024.3.6.0.dist-info/top_level.txt
ibm_developerworks_quanbu_jiaocheng_er-2024.3.6.0.dist-info/RECORD
